README.md
setup.py
wellsantos/__init__.py
wellsantos/dependency/__init__.py
wellsantos/dependency/close.py
wellsantos/dependency/factory.py
wellsantos/dependency/local.py
wellsantos/dependency/subclass.py
wellsantos/general/__init__.py
wellsantos/general/clock.py
wellsantos/general/enum.py
wellsantos/general/error.py
wellsantos/general/misc.py
wellsantos/general/model.py
wellsantos/general/settings.py
wellsantos/general/tracing.py
wellsantos_tools.egg-info/PKG-INFO
wellsantos_tools.egg-info/SOURCES.txt
wellsantos_tools.egg-info/dependency_links.txt
wellsantos_tools.egg-info/requires.txt
wellsantos_tools.egg-info/top_level.txt